README.txt
bootstrap.py
buildout.cfg
setup.py
bbdb/__init__.py
bbdb.gmailfilter.egg-info/PKG-INFO
bbdb.gmailfilter.egg-info/SOURCES.txt
bbdb.gmailfilter.egg-info/dependency_links.txt
bbdb.gmailfilter.egg-info/entry_points.txt
bbdb.gmailfilter.egg-info/namespace_packages.txt
bbdb.gmailfilter.egg-info/not-zip-safe
bbdb.gmailfilter.egg-info/requires.txt
bbdb.gmailfilter.egg-info/top_level.txt
bbdb/gmailfilter/README.txt
bbdb/gmailfilter/__init__.py
bbdb/gmailfilter/export.py
bbdb/gmailfilter/gmail-filter.pt
bbdb/gmailfilter/tests.py
docs/HISTORY.txt
site-lisp/bbdb-gmail-filter.el