Metadata-Version: 1.0
Name: bbdb.gmailfilter
Version: 0.4
Summary: Export BBDB contacts to gmail filter import XML
Home-page: http://pypi.python.org/pypi/bbdb.gmailfilter
Author: Ross Patterson
Author-email: me@rpatterson.net
License: GPL
Platform: UNKNOWN
Classifier: Programming Language :: Python
Classifier: Topic :: Software Development :: Libraries :: Python Modules
